qpid_bow/__init__.py
qpid_bow/asyncio.py
qpid_bow/config.py
qpid_bow/exc.py
qpid_bow/message.py
qpid_bow/receiver.py
qpid_bow/remote_procedure.py
qpid_bow/sender.py
qpid_bow/cli/__init__.py
qpid_bow/cli/connection_kill.py
qpid_bow/cli/message_receive.py
qpid_bow/cli/message_send.py
qpid_bow/cli/qpid_bow.py
qpid_bow/cli/queue_create.py
qpid_bow/cli/queue_delete.py
qpid_bow/cli/queue_purge.py
qpid_bow/cli/queue_reroute.py
qpid_bow/cli/queue_stats.py
qpid_bow/cli/route_config.py
qpid_bow/cli/route_dump.py
qpid_bow/cli/session_outgoing.py
qpid_bow/management/__init__.py
qpid_bow/management/connection.py
qpid_bow/management/exchange.py
qpid_bow/management/queue.py
qpid_bow/management/session.py
qpid_bow/management/statistics.py
qpid_bow-1.1.1.dist-info/METADATA
qpid_bow-1.1.1.dist-info/RECORD
qpid_bow-1.1.1.dist-info/WHEEL
qpid_bow-1.1.1.dist-info/entry_points.txt
qpid_bow-1.1.1.dist-info/top_level.txt
qpid_bow-1.1.1.dist-info/zip-safe
test/__init__.py
test/test_config.py
test/test_failover.py
test/test_management.py
test/test_message.py
test/test_receiver.py
test/test_rpc.py
test/test_sender.py
