Metadata-Version: 2.1
Name: qpid-bow
Version: 1.1.1
Summary: Set of tools to work with Qpid and a library for high-level Qpid interaction.
Home-page: https://github.com/Bynder/qpid-bow/
Author: Bynder
Author-email: info@bynder.com
License: MIT
Keywords: bynder
Platform: UNKNOWN
Classifier: Intended Audience :: Developers
Classifier: License :: OSI Approved :: MIT License
Classifier: Programming Language :: Python
Classifier: Programming Language :: Python :: 3
Classifier: Topic :: Software Development
Classifier: Topic :: Utilities
Provides-Extra: docs
Provides-Extra: test
Requires-Dist: python-qpid-proton (==0.24.0)
Requires-Dist: PyYAML (>=3.12)
Provides-Extra: docs
Requires-Dist: python-qpid-proton (==0.24.0); extra == 'docs'
Requires-Dist: PyYAML (>=3.12); extra == 'docs'
Requires-Dist: sphinx; extra == 'docs'
Requires-Dist: sphinx-rtd-theme; extra == 'docs'
Requires-Dist: sphinxcontrib-asyncio; extra == 'docs'
Provides-Extra: test
Requires-Dist: python-qpid-proton (==0.24.0); extra == 'test'
Requires-Dist: PyYAML (>=3.12); extra == 'test'
Requires-Dist: astroid (<1.6.0); extra == 'test'
Requires-Dist: bandit; extra == 'test'
Requires-Dist: mypy (==0.501); extra == 'test'
Requires-Dist: pylint (==1.7.0); extra == 'test'
Requires-Dist: pytest; extra == 'test'
Requires-Dist: pytest-cov; extra == 'test'
